word_game_solver/__about__.py
word_game_solver/__init__.py
word_game_solver/cli.py
word_game_solver/utils.py
word_game_solver/wordfinder.py
word_game_solver/info/LICENSE
word_game_solver/info/README.md
word_game_solver/info/about.txt
word_game_solver/info/help.md
word_game_solver/info/history.txt
word_game_solver/info/log.txt
word_game_solver/word_files/english_words.txt
word_game_solver-1.0.0.dist-info/licenses/LICENSE
word_game_solver-1.0.0.dist-info/METADATA
word_game_solver-1.0.0.dist-info/WHEEL
word_game_solver-1.0.0.dist-info/entry_points.txt
word_game_solver-1.0.0.dist-info/top_level.txt
word_game_solver-1.0.0.dist-info/RECORD
