Metadata-Version: 2.4
Name: word_game_solver
Version: 1.0.0
Summary: Generate valid English word sets based on a specified word length and a set of input characters using anagrams and a file with English words.
Author: Sharrrkkk
Maintainer: Sharrrkkk
License-Expression: MIT
Project-URL: Homepage, https://github.com/Sharrrkkk/word_game_solver
Project-URL: Documentation, https://github.com/Sharrrkkk/word_game_solver#README.md
Project-URL: Repository, https://github.com/Sharrrkkk/word_game_solver
Project-URL: Issues, https://github.com/Sharrrkkk/word_game_solver/issues
Keywords: anagram,anagrams,game,generate,word,words,solver,finder
Classifier: Development Status :: 5 - Production/Stable
Classifier: Intended Audience :: Education
Classifier: Intended Audience :: End Users/Desktop
Classifier: Topic :: Education
Classifier: Topic :: Games/Entertainment
Classifier: Programming Language :: Python :: 3
Requires-Python: >=3.10
License-File: LICENSE
Dynamic: license-file
